qink/__init__.py
qink/lib/__init__.c
qink/lib/__init__.cp312-win_amd64.pyd
qink/lib/__init__.py
qink/lib/config.c
qink/lib/config.cp312-win_amd64.pyd
qink/lib/config.py
qink/lib/core_api_client.c
qink/lib/core_api_client.cp312-win_amd64.pyd
qink/lib/core_api_client.py
qink/lib/logger.c
qink/lib/logger.cp312-win_amd64.pyd
qink/lib/logger.py
qink/lib/models.c
qink/lib/models.cp312-win_amd64.pyd
qink/lib/models.py
qink/lib/partitioner.c
qink/lib/partitioner.cp312-win_amd64.pyd
qink/lib/partitioner.py
qink/lib/process_function.c
qink/lib/process_function.cp312-win_amd64.pyd
qink/lib/process_function.py
qink/lib/qink.c
qink/lib/qink.cp312-win_amd64.pyd
qink/lib/qink.py
qink/lib/qink_assignment_listener.c
qink/lib/qink_assignment_listener.cp312-win_amd64.pyd
qink/lib/qink_assignment_listener.py
qink/lib/qink_azure_storage_provider.c
qink/lib/qink_azure_storage_provider.cp312-win_amd64.pyd
qink/lib/qink_azure_storage_provider.py
qink/lib/qink_kafka_source.c
qink/lib/qink_kafka_source.cp312-win_amd64.pyd
qink/lib/qink_kafka_source.py
qink/lib/qink_source.c
qink/lib/qink_source.cp312-win_amd64.pyd
qink/lib/qink_source.py
qink/lib/qink_storage.c
qink/lib/qink_storage.cp312-win_amd64.pyd
qink/lib/qink_storage.py
qink/lib/qink_storage_provider.c
qink/lib/qink_storage_provider.cp312-win_amd64.pyd
qink/lib/qink_storage_provider.py
qink/lib/qink_worker_process.c
qink/lib/qink_worker_process.cp312-win_amd64.pyd
qink/lib/qink_worker_process.py
qink-0.1.4.dist-info/licenses/LICENSE
tests/__init__.py
tests/conftest.py
tests/entry.py
tests/test_checkpoint.py
tests/test_partition_reassignment.py
tests/test_process_function.py
tests/test_qink_worker_process.py
tests/test_utils.py
qink-0.1.4.dist-info/METADATA
qink-0.1.4.dist-info/WHEEL
qink-0.1.4.dist-info/top_level.txt
qink-0.1.4.dist-info/RECORD
