Metadata-Version: 2.4
Name: qink
Version: 0.1.4
Summary: A real-time data processing framework
Author-email: Kosmas Papadatos <k.papadatos@quadible.co.uk>
Requires-Python: >=3.7
License-File: LICENSE
Requires-Dist: Cython>=3.0.12
Requires-Dist: setuptools>=78.1.0
Requires-Dist: pytest>=8.3.5
Requires-Dist: pytest-cov>=4.1.0
Requires-Dist: pytest-watch>=4.0.0
Requires-Dist: pytest-asyncio>=0.26.0
Requires-Dist: aiohttp>=3.9.0
Requires-Dist: azure-storage-blob>=12.19.0
Requires-Dist: python-dotenv>=1.1.0
Dynamic: license-file
